leiaapi/__init__.py
leiaapi/generated/__init__.py
leiaapi/generated/api_client.py
leiaapi/generated/configuration.py
leiaapi/generated/exceptions.py
leiaapi/generated/rest.py
leiaapi/generated/api/__init__.py
leiaapi/generated/api/annotation_api.py
leiaapi/generated/api/application_admin_api.py
leiaapi/generated/api/application_api.py
leiaapi/generated/api/document_admin_api.py
leiaapi/generated/api/document_api.py
leiaapi/generated/api/health_api.py
leiaapi/generated/api/job_admin_api.py
leiaapi/generated/api/job_api.py
leiaapi/generated/api/model_admin_api.py
leiaapi/generated/api/model_api.py
leiaapi/generated/api/worker_admin_api.py
leiaapi/generated/api/worker_api.py
leiaapi/generated/models/__init__.py
leiaapi/generated/models/annotation.py
leiaapi/generated/models/annotation_types.py
leiaapi/generated/models/application.py
leiaapi/generated/models/application_types.py
leiaapi/generated/models/apply_body.py
leiaapi/generated/models/classification.py
leiaapi/generated/models/conditional_body.py
leiaapi/generated/models/document.py
leiaapi/generated/models/format_types.py
leiaapi/generated/models/job.py
leiaapi/generated/models/job_result.py
leiaapi/generated/models/job_types.py
leiaapi/generated/models/login_body.py
leiaapi/generated/models/login_token.py
leiaapi/generated/models/model.py
leiaapi/generated/models/model_input_types.py
leiaapi/generated/models/model_types.py
leiaapi/generated/models/result_types.py
leiaapi/generated/models/speed.py
leiaapi/generated/models/statuses.py
leiaapi/generated/models/train_body.py
leiaapi/generated/models/transform_body.py
leiaapi/generated/models/transform_types.py
leiaapi/generated/models/worker.py
leiaapi/helpers/__init__.py
leiaapi/helpers/download.py
leiaapi/helpers/scheduler.py
leiaapi/helpers/session.py
leia_api_sdk-1.1.2.dist-info/LICENSE
leia_api_sdk-1.1.2.dist-info/METADATA
leia_api_sdk-1.1.2.dist-info/WHEEL
leia_api_sdk-1.1.2.dist-info/top_level.txt
leia_api_sdk-1.1.2.dist-info/RECORD
